setup.py
pdtlabcscovea9/_init_.py
pdtlabcscovea9.egg-info/PKG-INFO
pdtlabcscovea9.egg-info/SOURCES.txt
pdtlabcscovea9.egg-info/dependency_links.txt
pdtlabcscovea9.egg-info/not-zip-safe
pdtlabcscovea9.egg-info/top_level.txt